tssynth/__init__.py
tssynth/anomalies.py
tssynth/core.py
tssynth/dependencies.py
tssynth/noise.py
tssynth/patterns.py
tssynth/trends.py
tssynth-0.2.2.dist-info/METADATA
tssynth-0.2.2.dist-info/WHEEL
tssynth-0.2.2.dist-info/licenses/LICENSE
tssynth-0.2.2.dist-info/RECORD
