Metadata-Version: 2.4
Name: tssynth
Version: 0.2.2
Summary: A library for generating synthetic time series data
Author-email: Will Judge <williamjudge94@gmail.com>
License-File: LICENSE
Requires-Python: >=3.9
Requires-Dist: loguru>=0.6
Requires-Dist: numpy>=1.24
Requires-Dist: pandas>=2.0
Provides-Extra: dev
Requires-Dist: black>=22.0; extra == 'dev'
Requires-Dist: flake8>=4.0; extra == 'dev'
Requires-Dist: isort>=5.0; extra == 'dev'
Requires-Dist: pytest-cov>=4.0; extra == 'dev'
Requires-Dist: pytest>=7.0; extra == 'dev'
Provides-Extra: docs
Requires-Dist: myst-parser>=1.0; extra == 'docs'
Requires-Dist: sphinx-autodoc-typehints>=1.0; extra == 'docs'
Requires-Dist: sphinx-rtd-theme>=1.0; extra == 'docs'
Requires-Dist: sphinx>=7.0; extra == 'docs'
